sceepy/1_task.py
sceepy/2_task.py
sceepy/3_task.py
sceepy/4_task.py
sceepy/5_task.py
sceepy/6_task.py
sceepy/__init__.py
sceepy-0.3.dist-info/METADATA
sceepy-0.3.dist-info/WHEEL
sceepy-0.3.dist-info/top_level.txt
sceepy-0.3.dist-info/RECORD
