Metadata-Version: 2.1
Name: sceepy
Version: 0.3
Summary: Gaussian and Binomial distributions
Author-email: mihajlovic.aleksa@gmail.com
